[
  {
    "ngay": "2022-05-29",
    "giaoDich": [
      {"thoiGian": "16:37", "quyTaiChinh": "Thiết yếu", "theLoai": "Ăn uống", "soTien": 20000, "moTa": "Bánh tráng trộn"},
      {"thoiGian": "16:37", "quyTaiChinh": "Hưởng thụ", "theLoai": "Ăn uống", "soTien": 13000, "moTa": "Nước cam"},
      {"thoiGian": "16:37", "quyTaiChinh": "Thiết yếu", "theLoai": "Ăn uống", "soTien": 25000, "moTa": "Cơm xúc xích"},
      {"thoiGian": "10:06", "quyTaiChinh": "Thiết yếu", "theLoai": "Ăn uống", "soTien": 15000, "moTa": "Bún xào chay"}
    ],
    "tongThuNhap": 0,
    "tongChiTieu": 73000
  },
  {
    "ngay": "2022-05-28",
    "giaoDich": [
      {"thoiGian": "18:59", "quyTaiChinh": "Hưởng thụ", "theLoai": "Ăn uống", "soTien": 17000, "moTa": "Nha đam"},
      {"thoiGian": "18:59", "quyTaiChinh": "Thiết yếu", "theLoai": "Ăn uống", "soTien": 20000, "moTa": "Canh bún"},
      {"thoiGian": "14:32", "quyTaiChinh": "Thiết yếu", "theLoai": "Ăn uống", "soTien": 25000, "moTa": "Cơm trứng chiên"},
      {"thoiGian": "09:41", "quyTaiChinh": "Thiết yếu", "theLoai": "Ăn uống", "soTien": 25000, "moTa": "Bún bò"}
    ],
    "tongThuNhap": 0,
    "tongChiTieu": 87000
  },
  {
    "ngay": "2022-05-27",
    "giaoDich": [
      {"thoiGian": "18:46", "quyTaiChinh": "Thiết yếu", "theLoai": "Ăn uống", "soTien": 15000, "moTa": "Cơm chay"},
      {"thoiGian": "15:43", "quyTaiChinh": "Thiết yếu", "theLoai": "Ăn uống", "soTien": 25000, "moTa": "Cơm chả cá"},
      {"thoiGian": "10:11", "quyTaiChinh": "Thiết yếu", "theLoai": "Ăn uống", "soTien": 20000, "moTa": "Xôi mặn"}
    ],
    "tongThuNhap": 0,
    "tongChiTieu": 60000
  },
  {
    "ngay": "2022-05-26",
    "giaoDich": [
      {"thoiGian": "18:51", "quyTaiChinh": "Thiết yếu", "theLoai": "Ăn uống", "soTien": 20000, "moTa": "Mì gói khô"},
      {"thoiGian": "12:23", "quyTaiChinh": "Thiết yếu", "theLoai": "Ăn uống", "soTien": 25000, "moTa": "Cơm sườn kho"},
      {"thoiGian": "12:23", "quyTaiChinh": "Thiết yếu", "theLoai": "Ăn uống", "soTien": 20000, "moTa": "Bình nước 20l"},
      {"thoiGian": "08:14", "quyTaiChinh": "Thiết yếu", "theLoai": "Ăn uống", "soTien": 25000, "moTa": "Bún bò"}
    ],
    "tongThuNhap": 0,
    "tongChiTieu": 90000
  },
  {
    "ngay": "2022-05-25",
    "giaoDich": [
      {"thoiGian": "18:58", "quyTaiChinh": "Thiết yếu", "theLoai": "Ăn uống", "soTien": 20000, "moTa": "Nui"},
      {"thoiGian": "12:37", "quyTaiChinh": "Giáo dục", "theLoai": "Mua sách/tài liệu",  "soTien": 20000, "moTa": "Mua 2 bộ hồ sơ"},
      {"thoiGian": "12:37", "quyTaiChinh": "Thiết yếu", "theLoai": "Giao thông vận tải", "soTien": 3000, "moTa": "Giữ xe"},
      {"thoiGian": "12:37", "quyTaiChinh": "Thiết yếu", "theLoai": "Ăn uống", "soTien": 20000, "moTa": "Mì xào bò"}
    ],
    "tongThuNhap": 0,
    "tongChiTieu": 63000
  },
  {
    "ngay": "2022-05-24",
    "giaoDich": [
      {"thoiGian": "18:58", "quyTaiChinh": "Thiết yếu", "theLoai": "Ăn uống", "soTien": 20000, "moTa": "Hủ tiếu"},
      {"thoiGian": "18:58", "quyTaiChinh": "Hưởng thụ", "theLoai": "Ăn uống", "soTien": 10000, "moTa": "Nước mía"},
      {"thoiGian": "18:58", "quyTaiChinh": "Thiết yếu", "theLoai": "Ăn uống", "soTien": 25000, "moTa": "Cơm đậu hũ nhồi thịt"},
      {"thoiGian": "09:15", "quyTaiChinh": "Thiết yếu", "theLoai": "Ăn uống", "soTien": 15000, "moTa": "Mì quảng"}
    ],
    "tongThuNhap": 0,
    "tongChiTieu": 70000
  },
  {
    "ngay": "2022-05-23",
    "giaoDich": [
      {"thoiGian": "21:25", "quyTaiChinh": "Hưởng thụ", "theLoai": "Giặt sấy đồ", "soTien": 20000, "moTa": "Giặt mền, áo gối"},
      {"thoiGian": "18:52", "quyTaiChinh": "Thiết yếu", "theLoai": "Ăn uống", "soTien": 20000, "moTa": "Canh bún"},
      {"thoiGian": "13:18", "quyTaiChinh": "Thiết yếu", "theLoai": "Ăn uống", "soTien": 25000, "moTa": "Cơm tép"},
      {"thoiGian": "08:30", "quyTaiChinh": "Thiết yếu", "theLoai": "Ăn uống", "soTien": 12000, "moTa": "Bánh mì"},
      {"thoiGian": "08:30", "quyTaiChinh": "Thiết yếu", "theLoai": "Tiền trọ", "soTien": 830000, "moTa": "Tiền trọ"},
      {"thoiGian": "08:30", "quyTaiChinh": "", "theLoai": "", "soTien": 3500000, "moTa": "Má gửi"}
    ],
    "tongThuNhap": 3500000,
    "tongChiTieu": 907000
  },
  {
    "ngay": "2022-04-25",
    "giaoDich": [
      {"thoiGian": "18:44", "quyTaiChinh": "Thiết yếu", "theLoai": "Ăn uống", "soTien": 20000, "moTa": "Mì gói khô"},
      {"thoiGian": "12:54", "quyTaiChinh": "Hưởng thụ", "theLoai": "Ăn uống", "soTien": 10000, "moTa": "Nước mía"},
      {"thoiGian": "12:54", "quyTaiChinh": "Thiết yếu", "theLoai": "Ăn uống", "soTien": 18000, "moTa": "Cơm dương châu"},
      {"thoiGian": "08:45", "quyTaiChinh": "Thiết yếu", "theLoai": "Ăn uống", "soTien": 20000, "moTa": "Mì xào bò"}
    ],
    "tongThuNhap": 0,
    "tongChiTieu": 68000
  },
  {
    "ngay": "2022-04-24",
    "giaoDich": [
      {"thoiGian": "18:31", "quyTaiChinh": "Thiết yếu", "theLoai": "Ăn uống", "soTien": 20000, "moTa": "Hủ tiếu"},
      {"thoiGian": "14:35", "quyTaiChinh": "Hưởng thụ", "theLoai": "Ăn uống", "soTien": 12000, "moTa": "Cà phê sữa"},
      {"thoiGian": "14:35", "quyTaiChinh": "Thiết yếu", "theLoai": "Ăn uống", "soTien": 25000, "moTa": "Cơm thịt kho trứng"},
      {"thoiGian": "09:51", "quyTaiChinh": "Thiết yếu", "theLoai": "Ăn uống", "soTien": 15000, "moTa": "Xôi mặn"}
    ],
    "tongThuNhap": 0,
    "tongChiTieu": 72000
  },
  {
    "ngay": "2022-04-23",
    "giaoDich": [
      {"thoiGian": "18:40", "quyTaiChinh": "Thiết yếu", "theLoai": "Ăn uống", "soTien": 20000, "moTa": "Canh bún"},
      {"thoiGian": "18:40", "quyTaiChinh": "Thiết yếu", "theLoai": "Ăn uống", "soTien": 20000, "moTa": "Bình nước 20l"},
      {"thoiGian": "12:13", "quyTaiChinh": "Thiết yếu", "theLoai": "Ăn uống", "soTien": 20000, "moTa": "Cơm chiên"},
      {"thoiGian": "08:29", "quyTaiChinh": "Hưởng thụ", "theLoai": "Ăn uống", "soTien": 12000, "moTa": "Trà đào"},
      {"thoiGian": "08:29", "quyTaiChinh": "Thiết yếu", "theLoai": "Ăn uống", "soTien": 15000, "moTa": "Bún xào chay"}
    ],
    "tongThuNhap": 0,
    "tongChiTieu": 87000
  },
  {
    "ngay": "2022-04-22",
    "giaoDich": [
      {"thoiGian": "18:50", "quyTaiChinh": "Thiết yếu", "theLoai": "Ăn uống", "soTien": 20000, "moTa": "Hủ tiếu"},
      {"thoiGian": "18:50", "quyTaiChinh": "Thiết yếu", "theLoai": "Ăn uống", "soTien": 3300, "moTa": "Rút tiền"},
      {"thoiGian": "13:38", "quyTaiChinh": "Thiết yếu", "theLoai": "Ăn uống", "soTien": 20000, "moTa": "Cơm xúc xích"},
      {"thoiGian": "09:36", "quyTaiChinh": "Thiết yếu", "theLoai": "Ăn uống", "soTien": 15000, "moTa": "Cơm chay"}
    ],
    "tongThuNhap": 0,
    "tongChiTieu": 68300
  },
  {
    "ngay": "2022-04-21",
    "giaoDich": [
      {"thoiGian": "21:47", "quyTaiChinh": "Thiết yếu", "theLoai": "Ăn uống", "soTien": 40000, "moTa": "Hủ tiếu cùng Nhựt"},
      {"thoiGian": "21:47", "quyTaiChinh": "Thiết yếu", "theLoai": "Giao thông vận tải", "soTien": 6000, "moTa": "Giữ xe"},
      {"thoiGian": "21:47", "quyTaiChinh": "Hưởng thụ", "theLoai": "Ăn uống", "soTien": 51000, "moTa": "Ăn uống cùng Nhựt"},
      {"thoiGian": "08:29", "quyTaiChinh": "Thiết yếu", "theLoai": "Ăn uống", "soTien": 10000, "moTa": "Sữa đậu nành"},
      {"thoiGian": "08:29", "quyTaiChinh": "Thiết yếu", "theLoai": "Ăn uống", "soTien": 15000, "moTa": "Mì quảng"}
    ],
    "tongThuNhap": 0,
    "tongChiTieu": 122000
  },
  {
    "ngay": "2022-04-20",
    "giaoDich": [
      {"thoiGian": "18:59", "quyTaiChinh": "Thiết yếu", "theLoai": "Ăn uống", "soTien": 20000, "moTa": "Mì tươi thịt"},
      {"thoiGian": "14:05", "quyTaiChinh": "Thiết yếu", "theLoai": "Ăn uống", "soTien": 17000, "moTa": "Cơm ốp la"},
      {"thoiGian": "09:30", "quyTaiChinh": "Hưởng thụ", "theLoai": "Ăn uống", "soTien": 18000, "moTa": "Pepsi"},
      {"thoiGian": "09:30", "quyTaiChinh": "Thiết yếu", "theLoai": "Ăn uống", "soTien": 2000, "moTa": "Nước đá"},
      {"thoiGian": "09:30", "quyTaiChinh": "Thiết yếu", "theLoai": "Ăn uống", "soTien": 18000, "moTa": "Cơm xúc xích"}
    ],
    "tongThuNhap": 0,
    "tongChiTieu": 75000
  },
  {
    "ngay": "2022-04-19",
    "giaoDich": [
      {"thoiGian": "18:40", "quyTaiChinh": "Thiết yếu", "theLoai": "Ăn uống", "soTien": 20000, "moTa": "Canh bún"},
      {"thoiGian": "14:15", "quyTaiChinh": "Thiết yếu", "theLoai": "Ăn uống", "soTien": 25000, "moTa": "Cơm gà"},
      {"thoiGian": "09:31", "quyTaiChinh": "Hưởng thụ", "theLoai": "Ăn uống", "soTien": 12000, "moTa": "Trà đào"},
      {"thoiGian": "09:31", "quyTaiChinh": "Thiết yếu", "theLoai": "Ăn uống", "soTien": 12000, "moTa": "Bánh mì"}
    ],
    "tongThuNhap": 0,
    "tongChiTieu": 67000
  },
  {
    "ngay": "2022-04-18",
    "giaoDich": [
      {"thoiGian": "18:25", "quyTaiChinh": "Hưởng thụ", "theLoai": "Ăn uống", "soTien": 25000, "moTa": "Trà sữa"},
      {"thoiGian": "18:25", "quyTaiChinh": "Thiết yếu", "theLoai": "Ăn uống", "soTien": 20000, "moTa": "Mì gói"},
      {"thoiGian": "13:00", "quyTaiChinh": "Thiết yếu", "theLoai": "Ăn uống", "soTien": 20000, "moTa": "Cơm chiên"},
      {"thoiGian": "13:00", "quyTaiChinh": "Thiết yếu", "theLoai": "Ăn uống", "soTien": 15000, "moTa": "Cơm chay"}
    ],
    "tongThuNhap": 0,
    "tongChiTieu": 80000
  },
  {
    "ngay": "2022-04-17",
    "giaoDich": [
      {"thoiGian": "18:29", "quyTaiChinh": "Thiết yếu", "theLoai": "Ăn uống", "soTien": 10000, "moTa": "Cơm cháy"},
      {"thoiGian": "18:29", "quyTaiChinh": "Thiết yếu", "theLoai": "Giao thông vận tải", "soTien": 40000, "moTa": "Đổ xăng"},
      {"thoiGian": "18:29", "quyTaiChinh": "Thiết yếu", "theLoai": "Ăn uống", "soTien": 20000, "moTa": "Nui"},
      {"thoiGian": "13:21", "quyTaiChinh": "Thiết yếu", "theLoai": "Ăn uống", "soTien": 25000, "moTa": "Cơm xíu mại"},
      {"thoiGian": "13:21", "quyTaiChinh": "Thiết yếu", "theLoai": "Bank", "soTien": 3300, "moTa": "Rút tiền"},
      {"thoiGian": "09:00", "quyTaiChinh": "Thiết yếu", "theLoai": "Ăn uống", "soTien": 20000, "moTa": "Bình nước 20l"},
      {"thoiGian": "09:00", "quyTaiChinh": "Thiết yếu", "theLoai": "Ăn uống", "soTien": 15000, "moTa": "Xôi mặn"}
    ],
    "tongThuNhap": 0,
    "tongChiTieu": 133300
  },
  {
    "ngay": "2022-04-16",
    "giaoDich": [
      {"thoiGian": "18:22", "quyTaiChinh": "Thiết yếu", "theLoai": "Ăn uống", "soTien": 20000, "moTa": "Bánh canh"},
      {"thoiGian": "12:15", "quyTaiChinh": "Thiết yếu", "theLoai": "Ăn uống", "soTien": 25000, "moTa": "Cơm gà xối mỡ"},
      {"thoiGian": "12:15", "quyTaiChinh": "Thiết yếu", "theLoai": "Ăn uống", "soTien": 15000, "moTa": "Cơm chay"}
    ],
    "tongThuNhap": 0,
    "tongChiTieu": 60000
  },
  {
    "ngay": "2022-04-15",
    "giaoDich": [
      {"thoiGian": "18:38", "quyTaiChinh": "Hưởng thụ", "theLoai": "Ăn uống", "soTien": 22000, "moTa": "Trà sữa"},
      {"thoiGian": "18:38", "quyTaiChinh": "Thiết yếu", "theLoai": "Ăn uống", "soTien": 20000, "moTa": "Canh bún"},
      {"thoiGian": "13:08", "quyTaiChinh": "Thiết yếu", "theLoai": "Ăn uống", "soTien": 18000, "moTa": "Cơm xúc xích"},
      {"thoiGian": "10:05", "quyTaiChinh": "Thiết yếu", "theLoai": "Ăn uống", "soTien": 15000, "moTa": "Bún xào chay"}
    ],
    "tongThuNhap": 0,
    "tongChiTieu": 75000
  },
  {
    "ngay": "2022-04-14",
    "giaoDich": [
      {"thoiGian": "18:23", "quyTaiChinh": "Thiết yếu", "theLoai": "Ăn uống", "soTien": 20000, "moTa": "Hủ tiếu"},
      {"thoiGian": "14:34", "quyTaiChinh": "Hưởng thụ", "theLoai": "Ăn uống", "soTien": 20000, "moTa": "Dừa tắc"},
      {"thoiGian": "14:34", "quyTaiChinh": "Thiết yếu", "theLoai": "Ăn uống", "soTien": 18000, "moTa": "Cơm dương châu"},
      {"thoiGian": "08:47", "quyTaiChinh": "Thiết yếu", "theLoai": "Ăn uống", "soTien": 15000, "moTa": "Cơm chay"}
    ],
    "tongThuNhap": 0,
    "tongChiTieu": 73000
  },
  {
    "ngay": "2022-04-13",
    "giaoDich": [
      {"thoiGian": "19:01", "quyTaiChinh": "Thiết yếu", "theLoai": "Tiền trọ", "soTien": 870000, "moTa": "Tiền trọ"},
      {"thoiGian": "19:01", "quyTaiChinh": "Thiết yếu", "theLoai": "Ăn uống", "soTien": 20000, "moTa": "Nui"},
      {"thoiGian": "13:59", "quyTaiChinh": "Thiết yếu", "theLoai": "Ăn uống", "soTien": 25000, "moTa": "Cơm xúc xích"},
      {"thoiGian": "09:58", "quyTaiChinh": "Thiết yếu", "theLoai": "Bank",  "soTien": 3300, "moTa": "Rút tiền"},
      {"thoiGian": "09:58", "quyTaiChinh": "Thiết yếu", "theLoai": "Ăn uống", "soTien": 15000, "moTa": "Cơm chay"},{"thoiGian": "09:58", "quyTaiChinh": "", "theLoai": "", "soTien": 3500000, "moTa": "Má gửi"}
    ],
    "tongThuNhap": 3500000,
    "tongChiTieu": 933000
  },
  {
    "ngay": "2022-04-12",
    "giaoDich": [
      {"thoiGian": "19:01", "quyTaiChinh": "Thiết yếu", "theLoai": "Ăn uống", "soTien": 20000, "moTa": "Hủ tiếu"},
      {"thoiGian": "12:20", "quyTaiChinh": "Thiết yếu", "theLoai": "Ăn uống", "soTien": 20000, "moTa": "Cơm chiên"},
      {"thoiGian": "09:29", "quyTaiChinh": "Thiết yếu", "theLoai": "Ăn uống", "soTien": 13000, "moTa": "Bánh mì"}
    ],
    "tongThuNhap": 0,
    "tongChiTieu": 53000
  },
  {
    "ngay": "2022-04-11",
    "giaoDich": [
      {"thoiGian": "21:11", "quyTaiChinh": "Thiết yếu", "theLoai": "Ăn uống", "soTien": 20000, "moTa": "Bình nước 20l"},
      {"thoiGian": "21:11", "quyTaiChinh": "Thiết yếu", "theLoai": "Ăn uống", "soTien": 20000, "moTa": "Canh bún"},
      {"thoiGian": "21:11", "quyTaiChinh": "Thiết yếu", "theLoai": "Giao thông vận tải",  "soTien": 7000, "moTa": "Giữ xe"},
      {"thoiGian": "12:39", "quyTaiChinh": "Hưởng thụ", "theLoai": "Sức khỏe", "soTien": 30000, "moTa": "Dầu gió"}
    ],
    "tongThuNhap": 0,
    "tongChiTieu": 77000
  },
  {
    "ngay": "2022-04-10",
    "giaoDich": [
      {"thoiGian": "19:35", "quyTaiChinh": "Hưởng thụ", "theLoai": "Ăn uống", "soTien": 30000, "moTa": "Nước mía"},
      {"thoiGian": "19:33", "quyTaiChinh": "Thiết yếu", "theLoai": "Ăn uống", "soTien": 15000, "moTa": "Cơm gà xối mỡ"},
      {"thoiGian": "19:33", "quyTaiChinh": "Thiết yếu", "theLoai": "Giao thông vận tải", "soTien": 12000, "moTa": "Xe buýt"}
    ],
    "tongThuNhap": 0,
    "tongChiTieu": 57000
  },
  {
    "ngay": "2022-04-09",
    "giaoDich": [
      {"thoiGian": "18:47", "quyTaiChinh": "Thiết yếu", "theLoai": "Bank",  "soTien": 3300, "moTa": "Rút tiền"},
      {"thoiGian": "18:47", "quyTaiChinh": "Thiết yếu", "theLoai": "Ăn uống", "soTien": 20000, "moTa": "Mì gói"},
      {"thoiGian": "13:44", "quyTaiChinh": "Thiết yếu", "theLoai": "Ăn uống", "soTien": 25000, "moTa": "Cơm chả cá"},
      {"thoiGian": "09:59", "quyTaiChinh": "Hưởng thụ", "theLoai": "Ăn uống", "soTien": 12000, "moTa": "Cà phê sữa"},
      {"thoiGian": "09:59", "quyTaiChinh": "Thiết yếu", "theLoai": "Ăn uống", "soTien": 25000, "moTa": "Bún bò"}
    ],
    "tongThuNhap": 0,
    "tongChiTieu": 85300
  },
  {
    "ngay": "2022-04-08",
    "giaoDich": [
      {"thoiGian": "20:41", "quyTaiChinh": "Hưởng thụ", "theLoai": "Ăn uống", "soTien": 14000, "moTa": "Chè thập cẩm"},
      {"thoiGian": "20:41", "quyTaiChinh": "Thiết yếu", "theLoai": "Ăn uống", "soTien": 20000, "moTa": "Hủ tiếu"},
      {"thoiGian": "12:50", "quyTaiChinh": "Thiết yếu", "theLoai": "Ăn uống", "soTien": 25000, "moTa": "Cơm mực xào bông cải"},
      {"thoiGian": "09:53", "quyTaiChinh": "Thiết yếu", "theLoai": "Ăn uống", "soTien": 15000, "moTa": "Cơm xúc xích"}
    ],
    "tongThuNhap": 0,
    "tongChiTieu": 74000
  },
  {
    "ngay": "2022-04-07",
    "giaoDich": [
      {"thoiGian": "18:52", "quyTaiChinh": "Thiết yếu", "theLoai": "Giao thông vận tải", "soTien": 40000, "moTa": "Đổ xăng"},
      {"thoiGian": "18:51", "quyTaiChinh": "Thiết yếu", "theLoai": "Ăn uống", "soTien": 20000, "moTa": "Hoành thánh"},
      {"thoiGian": "13:29", "quyTaiChinh": "Thiết yếu", "theLoai": "Ăn uống", "soTien": 25000, "moTa": "Cơm hột vịt kho"},
      {"thoiGian": "08:55", "quyTaiChinh": "Thiết yếu", "theLoai": "Ăn uống", "soTien": 20000, "moTa": "Bún riêu cua"}
    ],
    "tongThuNhap": 0,
    "tongChiTieu": 105000
  },
  {
    "ngay": "2022-04-06",
    "giaoDich": [
      {"thoiGian": "19:06", "quyTaiChinh": "Thiết yếu", "theLoai": "Ăn uống", "soTien": 20000, "moTa": "Bún riêu"},
      {"thoiGian": "14:13", "quyTaiChinh": "Hưởng thụ", "theLoai": "Ăn uống", "soTien": 10000, "moTa": "Mứt dâu"},
      {"thoiGian": "14:13", "quyTaiChinh": "Thiết yếu", "theLoai": "Ăn uống", "soTien": 25000, "moTa": "Cơm sườn"},
      {"thoiGian": "09:56", "quyTaiChinh": "Thiết yếu", "theLoai": "Ăn uống", "soTien": 25000, "moTa": "Bún bò"}
    ],
    "tongThuNhap": 0,
    "tongChiTieu": 80000
  },
  {
    "ngay": "2022-04-05",
    "giaoDich": [
      {"thoiGian": "19:31", "quyTaiChinh": "Thiết yếu", "theLoai": "Ăn uống", "soTien": 20000, "moTa": "Mì gói khô"},
      {"thoiGian": "14:00", "quyTaiChinh": "Thiết yếu", "theLoai": "Ăn uống", "soTien": 25000, "moTa": "Cơm ruột khìa"},
      {"thoiGian": "09:26", "quyTaiChinh": "Thiết yếu", "theLoai": "Ăn uống", "soTien": 20000, "moTa": "Cơm bì chả"}
    ],
    "tongThuNhap": 0,
    "tongChiTieu": 65000
  },
  {
    "ngay": "2022-04-04",
    "giaoDich": [
      {"thoiGian": "19:29", "quyTaiChinh": "Thiết yếu", "theLoai": "Ăn uống", "soTien": 20000, "moTa": "Nui"},
      {"thoiGian": "13:35", "quyTaiChinh": "Thiết yếu", "theLoai": "Ăn uống", "soTien": 22000, "moTa": "Cơm hải sản"},
      {"thoiGian": "11:14", "quyTaiChinh": "Thiết yếu", "theLoai": "Ăn uống", "soTien": 20000, "moTa": "Bình nước 20l"},
      {"thoiGian": "09:38", "quyTaiChinh": "Hưởng thụ", "theLoai": "Ăn uống", "soTien": 12000, "moTa": "Cà phê sữa"},
      {"thoiGian": "09:38", "quyTaiChinh": "Thiết yếu", "theLoai": "Ăn uống", "soTien": 15000, "moTa": "Cơm chay"}
    ],
    "tongThuNhap": 0,
    "tongChiTieu": 89000
  },
  {
    "ngay": "2022-04-03",
    "giaoDich": [
      {"thoiGian": "19:27", "quyTaiChinh": "Thiết yếu", "theLoai": "Ăn uống", "soTien": 20000, "moTa": "Bánh canh"},
      {"thoiGian": "19:27", "quyTaiChinh": "Thiết yếu", "theLoai": "Bank",  "soTien": 3300, "moTa": "Rút tiền"},
      {"thoiGian": "14:00", "quyTaiChinh": "Hưởng thụ", "theLoai": "Ăn uống", "soTien": 10000, "moTa": "Chanh muối"},
      {"thoiGian": "14:00", "quyTaiChinh": "Thiết yếu", "theLoai": "Ăn uống", "soTien": 25000, "moTa": "Cơm đậu hũ nhồi thịt"},
      {"thoiGian": "10:12", "quyTaiChinh": "Thiết yếu", "theLoai": "Ăn uống", "soTien": 25000, "moTa": "Bún bò"}
    ],
    "tongThuNhap": 0,
    "tongChiTieu": 83300
  },
  {
    "ngay": "2022-04-02",
    "giaoDich": [
      {"thoiGian": "19:12", "quyTaiChinh": "Thiết yếu", "theLoai": "Ăn uống", "soTien": 20000, "moTa": "Canh bún"},
      {"thoiGian": "19:12", "quyTaiChinh": "Thiết yếu", "theLoai": "Ăn uống", "soTien": 25000, "moTa": "Cơm tép"},
      {"thoiGian": "08:43", "quyTaiChinh": "Thiết yếu", "theLoai": "Ăn uống", "soTien": 20000, "moTa": "Bún chả"}
    ],
    "tongThuNhap": 0,
    "tongChiTieu": 65000
  },
  {
    "ngay": "2022-04-01",
    "giaoDich": [
      {"thoiGian": "17:01", "quyTaiChinh": "Hưởng thụ", "theLoai": "Ăn uống", "soTien": 12000, "moTa": "Sinh tố chuối"},
      {"thoiGian": "17:01", "quyTaiChinh": "Thiết yếu", "theLoai": "Ăn uống", "soTien": 25000, "moTa": "Cơm thịt kho hột vịt"},
      {"thoiGian": "17:01", "quyTaiChinh": "Thiết yếu", "theLoai": "Ăn uống", "soTien": 20000, "moTa": "Mì gói"},
      {"thoiGian": "08:20", "quyTaiChinh": "Thiết yếu", "theLoai": "Ăn uống", "soTien": 25000, "moTa": "Phở bò"}
    ],
    "tongThuNhap": 0,
    "tongChiTieu": 82000
  },
  {
    "ngay": "2022-03-31",
    "giaoDich": [
      {"thoiGian": "19:19", "quyTaiChinh": "Thiết yếu", "theLoai": "Ăn uống", "soTien": 20000, "moTa": "Hủ tiếu"},
      {"thoiGian": "14:12", "quyTaiChinh": "Thiết yếu", "theLoai": "Ăn uống", "soTien": 17000, "moTa": "Cơm ốp la"},
      {"thoiGian": "08:55", "quyTaiChinh": "Thiết yếu", "theLoai": "Ăn uống", "soTien": 15000, "moTa": "Cơm chay"}
    ],
    "tongThuNhap": 0,
    "tongChiTieu": 52000
  },
  {
    "ngay": "2022-03-30",
    "giaoDich": [
      {"thoiGian": "20:30", "quyTaiChinh": "Thiết yếu", "theLoai": "Ăn uống", "soTien": 20000, "moTa": "Bánh canh"},
      {"thoiGian": "12:05", "quyTaiChinh": "Thiết yếu", "theLoai": "Ăn uống", "soTien": 25000, "moTa": "Cơm gà xối mỡ"},
      {"thoiGian": "08:51", "quyTaiChinh": "Thiết yếu", "theLoai": "Ăn uống",  "soTien": 2000, "moTa": "Nước đá"},
      {"thoiGian": "08:51", "quyTaiChinh": "Thiết yếu", "theLoai": "Ăn uống", "soTien": 20000, "moTa": "Cơm bì trứng"}
    ],
    "tongThuNhap": 0,
    "tongChiTieu": 67000
  },
  {
    "ngay": "2022-03-29",
    "giaoDich": [
      {"thoiGian": "21:49", "quyTaiChinh": "Thiết yếu", "theLoai": "Ăn uống", "soTien": 20000, "moTa": "Hủ tiếu"},
      {"thoiGian": "13:09", "quyTaiChinh": "Thiết yếu", "theLoai": "Ổ khóa", "soTien": 70000, "moTa": "Ổ khóa"},
      {"thoiGian": "13:09", "quyTaiChinh": "Hưởng thụ", "theLoai": "Ăn uống", "soTien": 15000, "moTa": "Chuối sấy"},
      {"thoiGian": "13:09", "quyTaiChinh": "Thiết yếu", "theLoai": "Ăn uống", "soTien": 25000, "moTa": "Cơm heo quay"},
      {"thoiGian": "11:10", "quyTaiChinh": "Thiết yếu", "theLoai": "Ăn uống",  "soTien": 2000, "moTa": "Nước đá"},
      {"thoiGian": "11:10", "quyTaiChinh": "Hưởng thụ", "theLoai": "Ăn uống", "soTien": 10000, "moTa": "Nước sữa chua"},
      {"thoiGian": "11:10", "quyTaiChinh": "Hưởng thụ", "theLoai": "Ăn uống",  "soTien": 9000, "moTa": "Bánh mì sữa"}
    ],
    "tongThuNhap": 0,
    "tongChiTieu": 151000
  },
  {
    "ngay": "2022-03-28",
    "giaoDich": [
      {"thoiGian": "17:25", "quyTaiChinh": "Thiết yếu", "theLoai": "Ăn uống", "soTien": 20000, "moTa": "Mì tươi thịt"},
      {"thoiGian": "12:36", "quyTaiChinh": "Thiết yếu", "theLoai": "Ăn uống", "soTien": 25000, "moTa": "Cơm sườn"},
      {"thoiGian": "12:36", "quyTaiChinh": "Thiết yếu", "theLoai": "Bank",  "soTien": 3300, "moTa": "Rút tiền"},
      {"thoiGian": "09:42", "quyTaiChinh": "Thiết yếu", "theLoai": "Ăn uống", "soTien": 20000, "moTa": "Bình nước 20l"},
      {"thoiGian": "09:31", "quyTaiChinh": "Thiết yếu", "theLoai": "Ăn uống",  "soTien": 2000, "moTa": "Nước đá"},
      {"thoiGian": "09:31", "quyTaiChinh": "Thiết yếu", "theLoai": "Ăn uống", "soTien": 25000, "moTa": "Bún bò"}
    ],
    "tongThuNhap": 0,
    "tongChiTieu": 95300
  },
  {
    "ngay": "2022-03-27",
    "giaoDich": [
      {"thoiGian": "19:25", "quyTaiChinh": "Thiết yếu", "theLoai": "Ăn uống", "soTien": 20000, "moTa": "Bánh canh"},
      {"thoiGian": "15:55", "quyTaiChinh": "Hưởng thụ", "theLoai": "Ăn uống", "soTien": 11000, "moTa": "Sting"},
      {"thoiGian": "15:55", "quyTaiChinh": "Thiết yếu", "theLoai": "Ăn uống", "soTien": 25000, "moTa": "Cơm cá chiên"},
      {"thoiGian": "10:04", "quyTaiChinh": "Thiết yếu", "theLoai": "Ăn uống",  "soTien": 2000, "moTa": "Nước đá"},
      {"thoiGian": "10:04", "quyTaiChinh": "Thiết yếu", "theLoai": "Ăn uống", "soTien": 15000, "moTa": "Mì quảng"}
    ],
    "tongThuNhap": 0,
    "tongChiTieu": 73000
  },
  {
    "ngay": "2022-03-26",
    "giaoDich": [
      {"thoiGian": "19:33", "quyTaiChinh": "Thiết yếu", "theLoai": "Ăn uống", "soTien": 20000, "moTa": "Hủ tiếu"},
      {"thoiGian": "13:58", "quyTaiChinh": "Hưởng thụ", "theLoai": "Ăn uống", "soTien": 20000, "moTa": "Sinh tố bơ"},
      {"thoiGian": "13:58", "quyTaiChinh": "Thiết yếu", "theLoai": "Ăn uống", "soTien": 22000, "moTa": "Cơm trứng chiên"},
      {"thoiGian": "09:08", "quyTaiChinh": "Thiết yếu", "theLoai": "Ăn uống",  "soTien": 2000, "moTa": "Nước đá"},
      {"thoiGian": "09:08", "quyTaiChinh": "Thiết yếu", "theLoai": "Ăn uống", "soTien": 20000, "moTa": "Bún chả"}
    ],
    "tongThuNhap": 0,
    "tongChiTieu": 84000
  },
  {
    "ngay": "2022-03-25",
    "giaoDich": [
      {"thoiGian": "19:50", "quyTaiChinh": "Thiết yếu", "theLoai": "Ăn uống", "soTien": 20000, "moTa": "Nui"},
      {"thoiGian": "09:57", "quyTaiChinh": "Thiết yếu", "theLoai": "Đồ dùng sinh hoạt", "soTien": 16000, "moTa": "Dầu gội"},
      {"thoiGian": "19:50", "quyTaiChinh": "Thiết yếu", "theLoai": "Ăn uống", "soTien": 25000, "moTa": "Cơm chả cá"},
      {"thoiGian": "09:57", "quyTaiChinh": "Thiết yếu", "theLoai": "Ăn uống",  "soTien": 2000, "moTa": "Nước đá"},
      {"thoiGian": "09:57", "quyTaiChinh": "Thiết yếu", "theLoai": "Ăn uống", "soTien": 25000, "moTa": "Bún bò"}
    ],
    "tongThuNhap": 0,
    "tongChiTieu": 88000
  },
  {
    "ngay": "2022-03-24",
    "giaoDich": [
      {"thoiGian": "19:07", "quyTaiChinh": "Thiết yếu", "theLoai": "Ăn uống", "soTien": 20000, "moTa": "Mì gói"},
      {"thoiGian": "14:54", "quyTaiChinh": "Hưởng thụ", "theLoai": "Ăn uống", "soTien": 12000, "moTa": "Trà Tắc Muối"},
      {"thoiGian": "14:54", "quyTaiChinh": "Thiết yếu", "theLoai": "Làm đẹp", "soTien": 45000, "moTa": "Hớt tóc"},
      {"thoiGian": "14:54", "quyTaiChinh": "Thiết yếu", "theLoai": "Ăn uống", "soTien": 25000, "moTa": "Cơm heo quay"},
      {"thoiGian": "08:55", "quyTaiChinh": "Thiết yếu", "theLoai": "Ăn uống",  "soTien": 2000, "moTa": "Nước đá"},
      {"thoiGian": "08:55", "quyTaiChinh": "Thiết yếu", "theLoai": "Ăn uống", "soTien": 20000, "moTa": "Cơm bì chả"}
    ],
    "tongThuNhap": 0,
    "tongChiTieu": 124000
  },
  {
    "ngay": "2022-03-23",
    "giaoDich": [
      {"thoiGian": "18:29", "quyTaiChinh": "Thiết yếu", "theLoai": "Giao thông vận tải", "soTien": 40000, "moTa": "Đổ xăng"},
      {"thoiGian": "18:29", "quyTaiChinh": "Thiết yếu", "theLoai": "Ăn uống", "soTien": 20000, "moTa": "Hủ tiếu"},
      {"thoiGian": "18:29", "quyTaiChinh": "Thiết yếu", "theLoai": "Bank",  "soTien": 3300, "moTa": "Phí rút tiền"},
      {"thoiGian": "12:23", "quyTaiChinh": "Thiết yếu", "theLoai": "Ăn uống", "soTien": 22000, "moTa": "Cơm sườn"},
      {"thoiGian": "09:32", "quyTaiChinh": "Thiết yếu", "theLoai": "Ăn uống",  "soTien": 2000, "moTa": "Nước đá"},
      {"thoiGian": "09:32", "quyTaiChinh": "Thiết yếu", "theLoai": "Ăn uống", "soTien": 25000, "moTa": "Bún bò"}
    ],
    "tongThuNhap": 0,
    "tongChiTieu": 112300
  },
  {
    "ngay": "2022-03-22",
    "giaoDich": [
      {"thoiGian": "18:48", "quyTaiChinh": "Thiết yếu", "theLoai": "Ăn uống", "soTien": 20000, "moTa": "Mì gói khô"},
      {"thoiGian": "14:09", "quyTaiChinh": "Thiết yếu", "theLoai": "Ăn uống", "soTien": 25000, "moTa": "Cơm xúc xích"},
      {"thoiGian": "09:28", "quyTaiChinh": "Thiết yếu", "theLoai": "Ăn uống",  "soTien": 2000, "moTa": "Nước đá"},
      {"thoiGian": "09:28", "quyTaiChinh": "Thiết yếu", "theLoai": "Ăn uống", "soTien": 15000, "moTa": "Mì quảng"}
    ],
    "tongThuNhap": 0,
    "tongChiTieu": 62000
  },
  {
    "ngay": "2022-03-21",
    "giaoDich": [
      {"thoiGian": "18:55", "quyTaiChinh": "Thiết yếu", "theLoai": "Ăn uống", "soTien": 20000, "moTa": "Bình nước 20l"},
      {"thoiGian": "18:55", "quyTaiChinh": "Thiết yếu", "theLoai": "Ăn uống", "soTien": 20000, "moTa": "Hoành thánh"},
      {"thoiGian": "13:55", "quyTaiChinh": "Thiết yếu", "theLoai": "Ăn uống", "soTien": 25000, "moTa": "Cơm chả cá"},
      {"thoiGian": "09:58", "quyTaiChinh": "Thiết yếu", "theLoai": "Ăn uống",  "soTien": 2000, "moTa": "Nước đá"},
      {"thoiGian": "09:58", "quyTaiChinh": "Thiết yếu", "theLoai": "Ăn uống", "soTien": 20000, "moTa": "Bún chả"}
    ],
    "tongThuNhap": 0,
    "tongChiTieu": 87000
  },
  {
    "ngay": "2022-03-20",
    "giaoDich": [
      {"thoiGian": "19:30", "quyTaiChinh": "Thiết yếu", "theLoai": "Ăn uống", "soTien": 20000, "moTa": "Nui"},
      {"thoiGian": "14:46", "quyTaiChinh": "Thiết yếu", "theLoai": "Ăn uống", "soTien": 22000, "moTa": "Cơm gà xối mỡ"},
      {"thoiGian": "13:51", "quyTaiChinh": "Hưởng thụ", "theLoai": "Ăn uống", "soTien": 10000, "moTa": "Trà không độ"},
      {"thoiGian": "10:12", "quyTaiChinh": "Thiết yếu", "theLoai": "Ăn uống",  "soTien": 2000, "moTa": "Nước đá"},
      {"thoiGian": "10:12", "quyTaiChinh": "Hưởng thụ", "theLoai": "Ăn uống", "soTien": 35000, "moTa": "Bánh, Sữa Proby"},
      {"thoiGian": "10:12", "quyTaiChinh": "Thiết yếu", "theLoai": "Ăn uống", "soTien": 20000, "moTa": "Cơm bì trứng"}
    ],
    "tongThuNhap": 0,
    "tongChiTieu": 109000
  },
  {
    "ngay": "2022-03-19",
    "giaoDich": [
      {"thoiGian": "18:35", "quyTaiChinh": "Thiết yếu", "theLoai": "Ăn uống", "soTien": 20000, "moTa": "Mì gói"},
      {"thoiGian": "12:27", "quyTaiChinh": "Thiết yếu", "theLoai": "Ăn uống", "soTien": 30000, "moTa": "Cơm mực kho xả"},
      {"thoiGian": "09:34", "quyTaiChinh": "Thiết yếu", "theLoai": "Ăn uống",  "soTien": 2000, "moTa": "Nước đá"},
      {"thoiGian": "09:34", "quyTaiChinh": "Thiết yếu", "theLoai": "Ăn uống", "soTien": 25000, "moTa": "Bún bò"}
    ],
    "tongThuNhap": 0,
    "tongChiTieu": 77000
  },
  {
    "ngay": "2022-03-18",
    "giaoDich": [
      {"thoiGian": "20:33", "quyTaiChinh": "Thiết yếu", "theLoai": "Sim", "soTien": 50000, "moTa": "Nạp tiền điện thoại"},
      {"thoiGian": "20:33", "quyTaiChinh": "Thiết yếu", "theLoai": "Ăn uống", "soTien": 20000, "moTa": "Nui"},
      {"thoiGian": "20:33", "quyTaiChinh": "Thiết yếu", "theLoai": "Ăn uống", "soTien": 25000, "moTa": "Cơm đậu hũ nhồi thịt"},
      {"thoiGian": "09:45", "quyTaiChinh": "Thiết yếu", "theLoai": "Ăn uống",  "soTien": 2000, "moTa": "Nước đá"},
      {"thoiGian": "09:45", "quyTaiChinh": "Thiết yếu", "theLoai": "Ăn uống", "soTien": 15000, "moTa": "Hủ tiếu chay"}
    ],
    "tongThuNhap": 0,
    "tongChiTieu": 112000
  },
  {
    "ngay": "2022-03-17",
    "giaoDich": [
      {"thoiGian": "19:29", "quyTaiChinh": "Thiết yếu", "theLoai": "Ăn uống", "soTien": 25000, "moTa": "Bánh canh"},
      {"thoiGian": "13:20", "quyTaiChinh": "Hưởng thụ", "theLoai": "Ăn uống", "soTien": 10000, "moTa": "Rau má"},
      {"thoiGian": "13:20", "quyTaiChinh": "Thiết yếu", "theLoai": "Ăn uống", "soTien": 22000, "moTa": "Cơm 2 ốp la"},
      {"thoiGian": "13:20", "quyTaiChinh": "Thiết yếu", "theLoai": "Bank",  "soTien": 3300, "moTa": "Phí rút tiền"},
      {"thoiGian": "08:47", "quyTaiChinh": "Thiết yếu", "theLoai": "Ăn uống",  "soTien": 2000, "moTa": "Nước đá"},
      {"thoiGian": "08:47", "quyTaiChinh": "Thiết yếu", "theLoai": "Ăn uống", "soTien": 25000, "moTa": "Bún bò"}
    ],
    "tongThuNhap": 0,
    "tongChiTieu": 87300
  },
  {
    "ngay": "2022-03-16",
    "giaoDich": [
      {"thoiGian": "19:03", "quyTaiChinh": "Thiết yếu", "theLoai": "Ăn uống", "soTien": 20000, "moTa": "Hủ tiếu"},
      {"thoiGian": "12:36", "quyTaiChinh": "Hưởng thụ", "theLoai": "Ăn uống", "soTien": 19000, "moTa": "Nước cam, sigum"},
      {"thoiGian": "12:36", "quyTaiChinh": "Thiết yếu", "theLoai": "Ăn uống", "soTien": 25000, "moTa": "Cơm gà xối mỡ"},
      {"thoiGian": "09:34", "quyTaiChinh": "Thiết yếu", "theLoai": "Ăn uống",  "soTien": 2000, "moTa": "Nước đá"},
      {"thoiGian": "09:34", "quyTaiChinh": "Thiết yếu", "theLoai": "Ăn uống", "soTien": 25000, "moTa": "Bún chả"}
    ],
    "tongThuNhap": 0,
    "tongChiTieu": 91000
  },
  {
    "ngay": "2022-03-15",
    "giaoDich": [
      {"thoiGian": "19:15", "quyTaiChinh": "Thiết yếu", "theLoai": "Ăn uống", "soTien": 20000, "moTa": "Bình nước 20l"},
      {"thoiGian": "19:15", "quyTaiChinh": "Thiết yếu", "theLoai": "Ăn uống", "soTien": 20000, "moTa": "Nui"},
      {"thoiGian": "14:06", "quyTaiChinh": "Thiết yếu", "theLoai": "Ăn uống", "soTien": 25000, "moTa": "Cơm sườn"},
      {"thoiGian": "09:53", "quyTaiChinh": "Thiết yếu", "theLoai": "Ăn uống",  "soTien": 3000, "moTa": "Nước đá"},
      {"thoiGian": "09:53", "quyTaiChinh": "Hưởng thụ", "theLoai": "Ăn uống", "soTien": 23000, "moTa": "Sữa chua Proby"},
      {"thoiGian": "09:53", "quyTaiChinh": "Thiết yếu", "theLoai": "Ăn uống", "soTien": 20000, "moTa": "Cơm bì trứng"}
    ],
    "tongThuNhap": 0,
    "tongChiTieu": 111000
  },
  {
    "ngay": "2022-03-14",
    "giaoDich": [
      {"thoiGian": "19:45", "quyTaiChinh": "Thiết yếu", "theLoai": "Ăn uống", "soTien": 20000, "moTa": "Mì gói"},
      {"thoiGian": "13:56", "quyTaiChinh": "Hưởng thụ", "theLoai": "Ăn uống", "soTien": 10000, "moTa": "Nước cam"},
      {"thoiGian": "13:56", "quyTaiChinh": "Thiết yếu", "theLoai": "Ăn uống", "soTien": 25000, "moTa": "Cơm trứng chiên"},
      {"thoiGian": "10:05", "quyTaiChinh": "Thiết yếu", "theLoai": "Sức khỏe", "soTien": 45000, "moTa": "Khẩu trang"},
      {"thoiGian": "10:05", "quyTaiChinh": "Thiết yếu", "theLoai": "Ăn uống",  "soTien": 2000, "moTa": "Nước đá"},
      {"thoiGian": "10:05", "quyTaiChinh": "Thiết yếu", "theLoai": "Ăn uống", "soTien": 15000, "moTa": "Mì quảng"}
    ],
    "tongThuNhap": 0,
    "tongChiTieu": 117000
  },
  {
    "ngay": "2022-03-13",
    "giaoDich": [
      {"thoiGian": "21:05", "quyTaiChinh": "Thiết yếu", "theLoai": "Tiền trọ", "soTien": 810000, "moTa": "Tiền trọ"},
      {"thoiGian": "19:42", "quyTaiChinh": "Thiết yếu", "theLoai": "Ăn uống", "soTien": 25000, "moTa": "Hủ tiếu"},
      {"thoiGian": "13:48", "quyTaiChinh": "Hưởng thụ", "theLoai": "Ăn uống", "soTien": 15000, "moTa": "Nước cam"},
      {"thoiGian": "13:48", "quyTaiChinh": "Thiết yếu", "theLoai": "Ăn uống", "soTien": 25000, "moTa": "Cơm đậu hũ nhồi thịt"},
      {"thoiGian": "09:23", "quyTaiChinh": "Thiết yếu", "theLoai": "Ăn uống",  "soTien": 2000, "moTa": "Nước đá"},
      {"thoiGian": "09:23", "quyTaiChinh": "Giáo dục", "theLoai": "Photo",  "soTien": 5000, "moTa": "Giấy A4"},
      {"thoiGian": "09:23", "quyTaiChinh": "Thiết yếu", "theLoai": "Ăn uống", "soTien": 25000, "moTa": "Bún bò"},{"thoiGian": "09:23", "quyTaiChinh": "", "theLoai": "", "soTien": 3500000, "moTa": "Má gửi"}
    ],
    "tongThuNhap": 3500000,
    "tongChiTieu": 907000
  },
  {
    "ngay": "2022-03-12",
    "giaoDich": [
      {"thoiGian": "19:21", "quyTaiChinh": "Thiết yếu", "theLoai": "Ăn uống", "soTien": 20000, "moTa": "Mì gói"},
      {"thoiGian": "12:50", "quyTaiChinh": "Hưởng thụ", "theLoai": "Ăn uống", "soTien": 10000, "moTa": "Nước cam"},
      {"thoiGian": "12:50", "quyTaiChinh": "Thiết yếu", "theLoai": "Ăn uống", "soTien": 22000, "moTa": "Cơm cá ngừ"},
      {"thoiGian": "09:08", "quyTaiChinh": "Thiết yếu", "theLoai": "Ăn uống",  "soTien": 2000, "moTa": "Nước đá"},
      {"thoiGian": "09:08", "quyTaiChinh": "Thiết yếu", "theLoai": "Ăn uống", "soTien": 25000, "moTa": "Cơm sườn"}
    ],
    "tongThuNhap": 0,
    "tongChiTieu": 79000
  },
  {
    "ngay": "2022-03-11",
    "giaoDich": [
      {"thoiGian": "17:45", "quyTaiChinh": "Thiết yếu", "theLoai": "Ăn uống", "soTien": 20000, "moTa": "Hoành thánh"},
      {"thoiGian": "17:45", "quyTaiChinh": "Thiết yếu", "theLoai": "Ăn uống",  "soTien": 6000, "moTa": "Nước suối"},
      {"thoiGian": "17:45", "quyTaiChinh": "Thiết yếu", "theLoai": "Ăn uống", "soTien": 25000, "moTa": "Cơm xíu mại"},
      {"thoiGian": "09:46", "quyTaiChinh": "Thiết yếu", "theLoai": "Ăn uống",  "soTien": 2000, "moTa": "Nước đá"},
      {"thoiGian": "09:46", "quyTaiChinh": "Thiết yếu", "theLoai": "Ăn uống", "soTien": 25000, "moTa": "Bún bò"}
    ],
    "tongThuNhap": 0,
    "tongChiTieu": 77000
  },
  {
    "ngay": "2022-03-10",
    "giaoDich": [
      {"thoiGian": "19:09", "quyTaiChinh": "Thiết yếu", "theLoai": "Ăn uống", "soTien": 20000, "moTa": "Bánh canh"},
      {"thoiGian": "12:47", "quyTaiChinh": "Thiết yếu", "theLoai": "Ăn uống", "soTien": 25000, "moTa": "Cơm bò xào rau cải"},
      {"thoiGian": "08:36", "quyTaiChinh": "Thiết yếu", "theLoai": "Ăn uống",  "soTien": 2000, "moTa": "Nước đá"},
      {"thoiGian": "08:36", "quyTaiChinh": "Thiết yếu", "theLoai": "Ăn uống", "soTien": 15000, "moTa": "Phở chay"}
    ],
    "tongThuNhap": 0,
    "tongChiTieu": 62000
  },
  {
    "ngay": "2022-03-09",
    "giaoDich": [
      {"thoiGian": "18:19", "quyTaiChinh": "Thiết yếu", "theLoai": "Ăn uống", "soTien": 20000, "moTa": "Hủ tiếu"},
      {"thoiGian": "18:19", "quyTaiChinh": "Thiết yếu", "theLoai": "Bank",  "soTien": 3300, "moTa": "Phí rút tiền"},
      {"thoiGian": "11:59", "quyTaiChinh": "Thiết yếu", "theLoai": "Ăn uống", "soTien": 25000, "moTa": "Cơm sườn"},
      {"thoiGian": "09:23", "quyTaiChinh": "Thiết yếu", "theLoai": "Ăn uống",  "soTien": 2000, "moTa": "Nước đá"},
      {"thoiGian": "09:23", "quyTaiChinh": "Thiết yếu", "theLoai": "Ăn uống", "soTien": 20000, "moTa": "Bún chả"}
    ],
    "tongThuNhap": 0,
    "tongChiTieu": 70300
  },
  {
    "ngay": "2022-03-08",
    "giaoDich": [
      {"thoiGian": "19:07", "quyTaiChinh": "Thiết yếu", "theLoai": "Giao thông vận tải", "soTien": 40000, "moTa": "Đổ xăng"},
      {"thoiGian": "19:07", "quyTaiChinh": "Thiết yếu", "theLoai": "Ăn uống", "soTien": 25000, "moTa": "Nui"},
      {"thoiGian": "18:19", "quyTaiChinh": "Thiết yếu", "theLoai": "Ăn uống", "soTien": 20000, "moTa": "Bình nước 20l"},
      {"thoiGian": "14:06", "quyTaiChinh": "Thiết yếu", "theLoai": "Ăn uống", "soTien": 25000, "moTa": "Cơm chả cá"},
      {"thoiGian": "09:40", "quyTaiChinh": "Thiết yếu", "theLoai": "Ăn uống",  "soTien": 2000, "moTa": "Nước đá"},
      {"thoiGian": "09:40", "quyTaiChinh": "Thiết yếu", "theLoai": "Ăn uống", "soTien": 15000, "moTa": "Cơm chay"}
    ],
    "tongThuNhap": 0,
    "tongChiTieu": 127000
  },
  {
    "ngay": "2022-03-07",
    "giaoDich": [
      {"thoiGian": "18:58", "quyTaiChinh": "Thiết yếu", "theLoai": "Ăn uống", "soTien": 20000, "moTa": "Hủ tiếu"},
      {"thoiGian": "13:52", "quyTaiChinh": "Hưởng thụ", "theLoai": "Ăn uống", "soTien": 10000, "moTa": "Chanh muối"},
      {"thoiGian": "13:52", "quyTaiChinh": "Thiết yếu", "theLoai": "Ăn uống", "soTien": 22000, "moTa": "Cơm cá kho"},
      {"thoiGian": "09:53", "quyTaiChinh": "Thiết yếu", "theLoai": "Ăn uống",  "soTien": 2000, "moTa": "Nước đá"},
      {"thoiGian": "09:53", "quyTaiChinh": "Thiết yếu", "theLoai": "Ăn uống", "soTien": 25000, "moTa": "Bún bò"}
    ],
    "tongThuNhap": 0,
    "tongChiTieu": 79000
  },
  {
    "ngay": "2022-03-06",
    "giaoDich": [
      {"thoiGian": "19:19", "quyTaiChinh": "Thiết yếu", "theLoai": "Ăn uống", "soTien": 20000, "moTa": "Mì gói"},
      {"thoiGian": "13:31", "quyTaiChinh": "Hưởng thụ", "theLoai": "Ăn uống", "soTien": 10000, "moTa": "Trà Tắc"},
      {"thoiGian": "13:31", "quyTaiChinh": "Thiết yếu", "theLoai": "Ăn uống", "soTien": 25000, "moTa": "Cơm sườn"},
      {"thoiGian": "09:55", "quyTaiChinh": "Thiết yếu", "theLoai": "Ăn uống",  "soTien": 2000, "moTa": "Nước đá"},
      {"thoiGian": "09:55", "quyTaiChinh": "Thiết yếu", "theLoai": "Ăn uống", "soTien": 15000, "moTa": "Mì quảng"}
    ],
    "tongThuNhap": 0,
    "tongChiTieu": 72000
  },
  {
    "ngay": "2022-03-05",
    "giaoDich": [
      {"thoiGian": "18:14", "quyTaiChinh": "Hưởng thụ", "theLoai": "Ăn uống",  "soTien": 7000, "moTa": "Sigum"},
      {"thoiGian": "18:14", "quyTaiChinh": "Thiết yếu", "theLoai": "Ăn uống",  "soTien": 2000, "moTa": "Hoành thánh"},
      {"thoiGian": "12:29", "quyTaiChinh": "Thiết yếu", "theLoai": "Ăn uống", "soTien": 25000, "moTa": "Cơm heo quay"},
      {"thoiGian": "09:30", "quyTaiChinh": "Thiết yếu", "theLoai": "Ăn uống",  "soTien": 2000, "moTa": "Nước đá"},
      {"thoiGian": "09:30", "quyTaiChinh": "Thiết yếu", "theLoai": "Ăn uống", "soTien": 25000, "moTa": "Phở bò"}
    ],
    "tongThuNhap": 0,
    "tongChiTieu": 61000
  },
  {
    "ngay": "2022-03-04",
    "giaoDich": [
      {"thoiGian": "18:07", "quyTaiChinh": "Hưởng thụ", "theLoai": "Ăn uống", "soTien": 20000, "moTa": "Nước cam"},
      {"thoiGian": "18:07", "quyTaiChinh": "Thiết yếu", "theLoai": "Ăn uống", "soTien": 20000, "moTa": "Mì gói khô"},
      {"thoiGian": "18:07", "quyTaiChinh": "Thiết yếu", "theLoai": "Ăn uống", "soTien": 25000, "moTa": "Cơm sườn"},
      {"thoiGian": "09:27", "quyTaiChinh": "Hưởng thụ", "theLoai": "Ăn uống",  "soTien": 6000, "moTa": "Nước sâm"},
      {"thoiGian": "09:27", "quyTaiChinh": "Thiết yếu", "theLoai": "Ăn uống",  "soTien": 2000, "moTa": "Nước đá"},
      {"thoiGian": "09:27", "quyTaiChinh": "Thiết yếu", "theLoai": "Ăn uống", "soTien": 20000, "moTa": "Cơm bì chả"}
    ],
    "tongThuNhap": 0,
    "tongChiTieu": 93000
  },
  {
    "ngay": "2022-03-03",
    "giaoDich": [
      {"thoiGian": "19:37", "quyTaiChinh": "Thiết yếu", "theLoai": "Bank",  "soTien": 3300, "moTa": "Rút tiền"},
      {"thoiGian": "19:05", "quyTaiChinh": "Thiết yếu", "theLoai": "Ăn uống", "soTien": 25000, "moTa": "Nui"},
      {"thoiGian": "13:59", "quyTaiChinh": "Hưởng thụ", "theLoai": "Ăn uống", "soTien": 12000, "moTa": "Bạc xỉu"},
      {"thoiGian": "13:59", "quyTaiChinh": "Thiết yếu", "theLoai": "Ăn uống", "soTien": 15000, "moTa": "Cơm ốp la"},
      {"thoiGian": "09:03", "quyTaiChinh": "Thiết yếu", "theLoai": "Ăn uống",  "soTien": 2000, "moTa": "Nước đá"},
      {"thoiGian": "09:03", "quyTaiChinh": "Thiết yếu", "theLoai": "Ăn uống", "soTien": 15000, "moTa": "Cơm chay"}
    ],
    "tongThuNhap": 0,
    "tongChiTieu": 72300
  },
  {
    "ngay": "2022-03-02",
    "giaoDich": [
      {"thoiGian": "19:03", "quyTaiChinh": "Thiết yếu", "theLoai": "Ăn uống", "soTien": 20000, "moTa": "Mì gói khô"},
      {"thoiGian": "12:39", "quyTaiChinh": "Thiết yếu", "theLoai": "Ăn uống", "soTien": 25000, "moTa": "Cơm đậu hũ nhồi thịt"},
      {"thoiGian": "09:47", "quyTaiChinh": "Thiết yếu", "theLoai": "Ăn uống",  "soTien": 2000, "moTa": "Nước đá"},
      {"thoiGian": "09:47", "quyTaiChinh": "Thiết yếu", "theLoai": "Ăn uống", "soTien": 20000, "moTa": "Bún chả"}
    ],
    "tongThuNhap": 0,
    "tongChiTieu": 67000
  },
  {
    "ngay": "2022-03-01",
    "giaoDich": [
      {"thoiGian": "18:26", "quyTaiChinh": "Thiết yếu", "theLoai": "Ăn uống", "soTien": 20000, "moTa": "Mì gói khô"},
      {"thoiGian": "14:01", "quyTaiChinh": "Thiết yếu", "theLoai": "Ăn uống", "soTien": 22000, "moTa": "Cơm chả cá"},
      {"thoiGian": "10:56", "quyTaiChinh": "Thiết yếu", "theLoai": "Ăn uống",  "soTien": 2000, "moTa": "Nước đá"},
      {"thoiGian": "10:56", "quyTaiChinh": "Thiết yếu", "theLoai": "Ăn uống", "soTien": 15000, "moTa": "Cơm xào trứng"}
    ],
    "tongThuNhap": 0,
    "tongChiTieu": 59000
  },
  {
    "ngay": "2022-02-28",
    "giaoDich": [
      {"thoiGian": "21:16", "quyTaiChinh": "Thiết yếu", "theLoai": "Ăn uống", "soTien": 20000, "moTa": "Bình nước 20l"},
      {"thoiGian": "18:00", "quyTaiChinh": "Thiết yếu", "theLoai": "Ăn uống", "soTien": 20000, "moTa": "Mì gói khô"},
      {"thoiGian": "13:30", "quyTaiChinh": "Thiết yếu", "theLoai": "Ăn uống", "soTien": 25000, "moTa": "Cơm heo quay"},
      {"thoiGian": "09:47", "quyTaiChinh": "Thiết yếu", "theLoai": "Ăn uống", "soTien": 25000, "moTa": "Phở bò"},
      {"thoiGian": "09:47", "quyTaiChinh": "Thiết yếu", "theLoai": "Ăn uống",  "soTien": 2000, "moTa": "Nước đá"}
    ],
    "tongThuNhap": 0,
    "tongChiTieu": 92000
  },
  {
    "ngay": "2022-02-27",
    "giaoDich": [
      {"thoiGian": "18:46", "quyTaiChinh": "Thiết yếu", "theLoai": "Giao thông vận tải",  "soTien": 7000, "moTa": "Giữ xe"},
      {"thoiGian": "18:46", "quyTaiChinh": "Hưởng thụ", "theLoai": "Ăn uống", "soTien": 35000, "moTa": "Bún đậu mắm tôm"},
      {"thoiGian": "18:45", "quyTaiChinh": "Hưởng thụ", "theLoai": "Ăn uống", "soTien": 41000, "moTa": "Pizza, Dr.Thanh, CocaCola"},
      {"thoiGian": "08:49", "quyTaiChinh": "Hưởng thụ", "theLoai": "Ăn uống", "soTien": 12000, "moTa": "Nước mía"},
      {"thoiGian": "08:49", "quyTaiChinh": "Thiết yếu", "theLoai": "Ăn uống", "soTien": 12000, "moTa": "Cơm chay"}
    ],
    "tongThuNhap": 0,
    "tongChiTieu": 107000
  },
  {
    "ngay": "2022-02-26",
    "giaoDich": [
      {"thoiGian": "18:03", "quyTaiChinh": "Thiết yếu", "theLoai": "Ăn uống", "soTien": 20000, "moTa": "Mì tươi khô"},
      {"thoiGian": "12:15", "quyTaiChinh": "Thiết yếu", "theLoai": "Ăn uống", "soTien": 25000, "moTa": "Cơm xíu mại"},
      {"thoiGian": "08:50", "quyTaiChinh": "Thiết yếu", "theLoai": "Ăn uống",  "soTien": 2000, "moTa": "Nước đá"},
      {"thoiGian": "08:50", "quyTaiChinh": "Thiết yếu", "theLoai": "Ăn uống", "soTien": 13000, "moTa": "Cơm chay"}
    ],
    "tongThuNhap": 0,
    "tongChiTieu": 60000
  },
  {
    "ngay": "2022-02-25",
    "giaoDich": [
      {"thoiGian": "18:11", "quyTaiChinh": "Thiết yếu", "theLoai": "Ăn uống", "soTien": 15000, "moTa": "Nước vải"},
      {"thoiGian": "18:11", "quyTaiChinh": "Thiết yếu", "theLoai": "Ăn uống", "soTien": 30000, "moTa": "Mì khô 2 gói"},
      {"thoiGian": "18:11", "quyTaiChinh": "Thiết yếu", "theLoai": "Ăn uống", "soTien": 25000, "moTa": "Cơm sườn"},
      {"thoiGian": "09:46", "quyTaiChinh": "Thiết yếu", "theLoai": "Ăn uống",  "soTien": 2000, "moTa": "Nước đá"},
      {"thoiGian": "09:46", "quyTaiChinh": "Thiết yếu", "theLoai": "Ăn uống", "soTien": 20000, "moTa": "Bún xào thịt nướng"}
    ],
    "tongThuNhap": 0,
    "tongChiTieu": 92000
  },
  {
    "ngay": "2022-02-24",
    "giaoDich": [
      {"thoiGian": "18:57", "quyTaiChinh": "Thiết yếu", "theLoai": "Ăn uống", "soTien": 20000, "moTa": "Mì gói khô"},
      {"thoiGian": "13:27", "quyTaiChinh": "Thiết yếu", "theLoai": "Ăn uống", "soTien": 20000, "moTa": "Cơm hải sản"},
      {"thoiGian": "08:31", "quyTaiChinh": "Thiết yếu", "theLoai": "Ăn uống",  "soTien": 2000, "moTa": "Nước đá"},
      {"thoiGian": "08:31", "quyTaiChinh": "Thiết yếu", "theLoai": "Ăn uống", "soTien": 20000, "moTa": "Cơm bì trứng"}
    ],
    "tongThuNhap": 0,
    "tongChiTieu": 62000
  },
  {
    "ngay": "2022-02-23",
    "giaoDich": [
      {"thoiGian": "18:12", "quyTaiChinh": "Thiết yếu", "theLoai": "Ăn uống", "soTien": 20000, "moTa": "Hủ tiếu"},
      {"thoiGian": "12:32", "quyTaiChinh": "Thiết yếu", "theLoai": "Ăn uống", "soTien": 25000, "moTa": "Cơm trứng chiên"},
      {"thoiGian": "08:50", "quyTaiChinh": "Thiết yếu", "theLoai": "Ăn uống",  "soTien": 2000, "moTa": "Nước đá"},
      {"thoiGian": "08:50", "quyTaiChinh": "Thiết yếu", "theLoai": "Ăn uống", "soTien": 25000, "moTa": "Phở bò"}
    ],
    "tongThuNhap": 0,
    "tongChiTieu": 72000
  },
  {
    "ngay": "2022-02-22",
    "giaoDich": [
      {"thoiGian": "19:32", "quyTaiChinh": "Thiết yếu", "theLoai": "Ăn uống", "soTien": 20000, "moTa": "Bánh canh"},
      {"thoiGian": "19:32", "quyTaiChinh": "Hưởng thụ", "theLoai": "Ăn uống", "soTien": 13000, "moTa": "Nước cam, bánh snack phomai"},
      {"thoiGian": "19:32", "quyTaiChinh": "Thiết yếu", "theLoai": "Đồ dùng sinh hoạt", "soTien": 129000, "moTa": "Sữa tắm"},
      {"thoiGian": "13:42", "quyTaiChinh": "Thiết yếu", "theLoai": "Ăn uống", "soTien": 22000, "moTa": "Cơm cá ngừ kho khóm"},
      {"thoiGian": "09:31", "quyTaiChinh": "Thiết yếu", "theLoai": "Ăn uống",  "soTien": 2000, "moTa": "Nước đá"},
      {"thoiGian": "09:31", "quyTaiChinh": "Thiết yếu", "theLoai": "Ăn uống", "soTien": 15000, "moTa": "Cơm"}
    ],
    "tongThuNhap": 0,
    "tongChiTieu": 201000
  },
  {
    "ngay": "2022-02-21",
    "giaoDich": [
      {"thoiGian": "17:46", "quyTaiChinh": "Thiết yếu", "theLoai": "Giao thông vận tải",  "soTien": 3000, "moTa": "Giữ xe"},
      {"thoiGian": "17:46", "quyTaiChinh": "Thiết yếu", "theLoai": "Ăn uống", "soTien": 20000, "moTa": "Mì gói"},
      {"thoiGian": "13:25", "quyTaiChinh": "Thiết yếu", "theLoai": "Ăn uống", "soTien": 25000, "moTa": "Cơm da gà"},
      {"thoiGian": "10:13", "quyTaiChinh": "Thiết yếu", "theLoai": "Ăn uống",  "soTien": 2000, "moTa": "Nước đá"},
      {"thoiGian": "10:13", "quyTaiChinh": "Thiết yếu", "theLoai": "Ăn uống", "soTien": 15000, "moTa": "Cơm cá kho khóm chay"}
    ],
    "tongThuNhap": 0,
    "tongChiTieu": 65000
  },
  {
    "ngay": "2022-02-20",
    "giaoDich": [
      {"thoiGian": "18:42", "quyTaiChinh": "Thiết yếu", "theLoai": "Ăn uống", "soTien": 20000, "moTa": "Bình nước 20l"},
      {"thoiGian": "18:42", "quyTaiChinh": "Thiết yếu", "theLoai": "Ăn uống", "soTien": 20000, "moTa": "Hủ tiếu"},
      {"thoiGian": "18:42", "quyTaiChinh": "Hưởng thụ", "theLoai": "Ăn uống", "soTien": 13000, "moTa": "Nước trà đào, sigum"},
      {"thoiGian": "14:32", "quyTaiChinh": "Giáo dục", "theLoai": "Photo",  "soTien": 8000, "moTa": "Photo"},
      {"thoiGian": "14:32", "quyTaiChinh": "Thiết yếu", "theLoai": "Ăn uống", "soTien": 25000, "moTa": "Cơm sườn"},
      {"thoiGian": "10:15", "quyTaiChinh": "Thiết yếu", "theLoai": "Ăn uống",  "soTien": 2000, "moTa": "Nước đá"},
      {"thoiGian": "10:15", "quyTaiChinh": "Thiết yếu", "theLoai": "Ăn uống", "soTien": 15000, "moTa": "Cơm chay"}
    ],
    "tongThuNhap": 0,
    "tongChiTieu": 102000
  },
  {
    "ngay": "2022-02-19",
    "giaoDich": [
      {"thoiGian": "18:15", "quyTaiChinh": "Thiết yếu", "theLoai": "Ăn uống", "soTien": 20000, "moTa": "Mì gói"},
      {"thoiGian": "12:07", "quyTaiChinh": "Thiết yếu", "theLoai": "Ăn uống", "soTien": 25000, "moTa": "Cơm xúc xích"},
      {"thoiGian": "09:19", "quyTaiChinh": "Thiết yếu", "theLoai": "Ăn uống",  "soTien": 2000, "moTa": "Nước đá"},
      {"thoiGian": "09:19", "quyTaiChinh": "Thiết yếu", "theLoai": "Ăn uống", "soTien": 25000, "moTa": "Bún riêu cua"}
    ],
    "tongThuNhap": 0,
    "tongChiTieu": 72000
  },
  {
    "ngay": "2022-02-18",
    "giaoDich": [
      {"thoiGian": "20:00", "quyTaiChinh": "Thiết yếu", "theLoai": "Giao thông vận tải", "soTien": 50000, "moTa": "Đổ xăng"},
      {"thoiGian": "20:00", "quyTaiChinh": "Thiết yếu", "theLoai": "Ăn uống", "soTien": 20000, "moTa": "Nui"},
      {"thoiGian": "14:05", "quyTaiChinh": "Thiết yếu", "theLoai": "Ăn uống", "soTien": 25000, "moTa": "Cơm đậu hũ nhồi thịt"},
      {"thoiGian": "09:54", "quyTaiChinh": "Thiết yếu", "theLoai": "Ăn uống",  "soTien": 2000, "moTa": "Nước đá"},
      {"thoiGian": "09:54", "quyTaiChinh": "Thiết yếu", "theLoai": "Ăn uống", "soTien": 18000, "moTa": "Mì xào xúc xích"}
    ],
    "tongThuNhap": 0,
    "tongChiTieu": 115000
  },
  {
    "ngay": "2022-02-17",
    "giaoDich": [
      {"thoiGian": "19:05", "quyTaiChinh": "Thiết yếu", "theLoai": "Ăn uống", "soTien": 20000, "moTa": "Hủ tiếu"},
      {"thoiGian": "16:11", "quyTaiChinh": "Thiết yếu", "theLoai": "Sim", "soTien": 52000, "moTa": "Mua sim Vietnamobile"},
      {"thoiGian": "16:11", "quyTaiChinh": "Thiết yếu", "theLoai": "Ăn uống", "soTien": 25000, "moTa": "Cơm mực kho xả"},
      {"thoiGian": "08:00", "quyTaiChinh": "Thiết yếu", "theLoai": "Ăn uống",  "soTien": 2000, "moTa": "Nước đá"},
      {"thoiGian": "08:00", "quyTaiChinh": "Thiết yếu", "theLoai": "Ăn uống", "soTien": 25000, "moTa": "Bún bò"}
    ],
    "tongThuNhap": 0,
    "tongChiTieu": 124000
  },
  {
    "ngay": "2022-02-16",
    "giaoDich": [
      {"thoiGian": "18:29", "quyTaiChinh": "Thiết yếu", "theLoai": "Sim", "soTien": 30000, "moTa": "Nạp tiền điện thoại"},
      {"thoiGian": "18:29", "quyTaiChinh": "Thiết yếu", "theLoai": "Ăn uống", "soTien": 20000, "moTa": "Mì tươi thịt"},
      {"thoiGian": "12:07", "quyTaiChinh": "Thiết yếu", "theLoai": "Ăn uống", "soTien": 22000, "moTa": "Cơm chả cá"},
      {"thoiGian": "10:01", "quyTaiChinh": "Thiết yếu", "theLoai": "Ăn uống",  "soTien": 2000, "moTa": "Nước đá"},
      {"thoiGian": "10:01", "quyTaiChinh": "Thiết yếu", "theLoai": "Ăn uống", "soTien": 15000, "moTa": "Cơm chả cá chay"}
    ],
    "tongThuNhap": 0,
    "tongChiTieu": 89000
  },
  {
    "ngay": "2022-02-15",
    "giaoDich": [
      {"thoiGian": "18:58", "quyTaiChinh": "Thiết yếu", "theLoai": "Ăn uống", "soTien": 20000, "moTa": "Hoành thánh"},
      {"thoiGian": "14:03", "quyTaiChinh": "Thiết yếu", "theLoai": "Ăn uống", "soTien": 25000, "moTa": "Cơm gà xối mỡ"},
      {"thoiGian": "10:09", "quyTaiChinh": "Thiết yếu", "theLoai": "Ăn uống", "soTien": 2000, "moTa": "Nước đá"},
      {"thoiGian": "10:09", "quyTaiChinh": "Thiết yếu", "theLoai": "Ăn uống", "soTien": 17000, "moTa": "Mì xào bò"}
    ],
    "tongThuNhap": 0,
    "tongChiTieu": 64000
  },
  {
    "ngay": "2022-02-14",
    "giaoDich": [
      {"thoiGian": "18:01", "quyTaiChinh": "Thiết yếu", "theLoai": "Ăn uống", "soTien": 20000, "moTa": "Bánh canh"},
      {"thoiGian": "13:43", "quyTaiChinh": "Thiết yếu", "theLoai": "Ăn uống", "soTien": 25000, "moTa": "Cơm cá chiên"},
      {"thoiGian": "09:57", "quyTaiChinh": "Thiết yếu", "theLoai": "Ăn uống", "soTien": 2000, "moTa": "Nước đá"},
      {"thoiGian": "09:57", "quyTaiChinh": "Thiết yếu", "theLoai": "Ăn uống", "soTien": 15000, "moTa": "Cơm chay"}
    ],
    "tongThuNhap": 0,
    "tongChiTieu": 62000
  },
  {
    "ngay": "2022-02-13",
    "giaoDich": [
      {"thoiGian": "19:40", "quyTaiChinh": "Hưởng thụ", "theLoai": "Giặt sấy đồ", "soTien": 20000, "moTa": "Giặt mền, áo gối"},
      {"thoiGian": "19:40", "quyTaiChinh": "Thiết yếu", "theLoai": "Ăn uống", "soTien": 20000, "moTa": "Hủ tiếu"},
      {"thoiGian": "17:08", "quyTaiChinh": "Thiết yếu", "theLoai": "Ăn uống", "soTien": 20000, "moTa": "Bình nước 20l"},
      {"thoiGian": "17:08", "quyTaiChinh": "Thiết yếu", "theLoai": "Ăn uống", "soTien": 25000, "moTa": "Cơm xúc xích"},
      {"thoiGian": "13:03", "quyTaiChinh": "Thiết yếu", "theLoai": "Giao thông vận tải", "soTien": 30000, "moTa": "Đổ xăng"},
      {"thoiGian": "13:03", "quyTaiChinh": "Thiết yếu", "theLoai": "Giao thông vận tải", "soTien": 5000, "moTa": "Bơm bánh xe"},
      {"thoiGian": "13:03", "quyTaiChinh": "Thiết yếu", "theLoai": "Giao thông vận tải", "soTien": 90000, "moTa": "Thay nhớt, rửa xe"},
      {"thoiGian": "09:07", "quyTaiChinh": "Thiết yếu", "theLoai": "Ăn uống", "soTien": 15000, "moTa": "Bún huế chay"},
      {"thoiGian": "09:07", "quyTaiChinh": "Thiết yếu", "theLoai": "Ăn uống", "soTien": 2000, "moTa": "Nước đá"}
    ],
    "tongThuNhap": 0,
    "tongChiTieu": 227000
  }
]